qualtricssurvey/__init__.py
qualtricssurvey/models.py
qualtricssurvey/settings.py
qualtricssurvey/views.py
qualtricssurvey/xblocks.py
qualtricssurvey/mixins/__init__.py
qualtricssurvey/mixins/fragment.py
qualtricssurvey/mixins/scenario.py
qualtricssurvey/public/view.css
qualtricssurvey/public/view.js
qualtricssurvey/public/view.less
qualtricssurvey/scenarios/qualtrics-survey-multiple-custom.xml
qualtricssurvey/scenarios/qualtrics-survey-single-simple.xml
qualtricssurvey/templates/view.html
qualtricssurvey/tests/__init__.py
qualtricssurvey/tests/test_display.py
qualtricssurvey/tests/test_workbench.py
xblock_qualtrics_survey-2.1.1.dist-info/licenses/LICENSE
xblock_qualtrics_survey-2.1.1.dist-info/METADATA
xblock_qualtrics_survey-2.1.1.dist-info/WHEEL
xblock_qualtrics_survey-2.1.1.dist-info/entry_points.txt
xblock_qualtrics_survey-2.1.1.dist-info/top_level.txt
xblock_qualtrics_survey-2.1.1.dist-info/RECORD
